setup.cfg
setup.py
scripts/ystratus.py
test/test_yamlstratus.py
yamlstratus/__init__.py
yamlstratus/yamlstratus.py
yamlstratus.egg-info/PKG-INFO
yamlstratus.egg-info/SOURCES.txt
yamlstratus.egg-info/dependency_links.txt
yamlstratus.egg-info/pbr.json
yamlstratus.egg-info/requires.txt
yamlstratus.egg-info/top_level.txt