Metadata-Version: 1.1
Name: yamlstratus
Version: 1.0.3
Summary: Python for yamlstratus builder
Home-page: https://github.com/kikinteractive/yaml-stratus/
Author: Kik Interactive
Author-email: UNKNOWN
License: Apache Software License
Download-URL: https://github.com/kikinteractive/yaml-stratus/tarball/0.1
Platform: any
Classifier: Programming Language :: Python
Classifier: Natural Language :: English
Classifier: Environment :: Web Environment
Classifier: Intended Audience :: Developers
Classifier: License :: OSI Approved :: Apache Software License
Classifier: Operating System :: OS Independent
Classifier: Topic :: Software Development :: Libraries :: Python Modules
Classifier: Topic :: Text Processing :: Markup
Classifier: Programming Language :: Python :: 2.6
Classifier: Programming Language :: Python :: 2.7
